{
  "stationCollection": [
    {
      "id": "01",
      "name": "Tramore",
      "readings": [
        {
          "date": "2021-01-19T08:31:00.000Z",
          "code": 800,
          "temperature": 0.5,
          "windSpeed": 3.5,
          "windDirection": 220,
          "pressure": 1001
        },
        {
          "id": "03",
          "date": "2021-01-20T09:34:00.000Z",
          "code": 600,
          "temperature": 6,
          "windSpeed": 2,
          "windDirection": 200,
          "pressure": 1004
        }
      ]
    },
    {
      "id": "05",
      "name": "Dunmore",
      "readings": [
        {
          "id": "06",
          "date": "2021-01-19T09:31:00.000Z",
          "code": 200,
          "temperature": 0.5,
          "windSpeed": 3.5,
          "windDirection": 120,
          "pressure": 999
        },
        {
          "id": "07",
          "code": 200,
          "temperature": 0.5,
          "windSpeed": 3.5,
          "windDirection": 200,
          "pressure": 1004
        }
      ]
    },
    {
      "id": "be39c610-0778-11ec-abe6-9ff11aa985c9",
      "name": "Ardmore",
      "readings": []
    }
  ]
}